aikoai/__init__.py
aikoai/_aikoai_scripts.py
aikoai/aikoai_object.py
aikoai/aikoai_response.py
aikoai/api_requestor.py
aikoai/cli.py
aikoai/embeddings_utils.py
aikoai/error.py
aikoai/object_classes.py
aikoai/py.typed
aikoai/upload_progress.py
aikoai/util.py
aikoai/validators.py
aikoai/version.py
aikoai/wandb_logger.py
aikoai/api_resources/__init__.py
aikoai/api_resources/audio.py
aikoai/api_resources/chat_completion.py
aikoai/api_resources/completion.py
aikoai/api_resources/customer.py
aikoai/api_resources/deployment.py
aikoai/api_resources/edit.py
aikoai/api_resources/embedding.py
aikoai/api_resources/engine.py
aikoai/api_resources/error_object.py
aikoai/api_resources/file.py
aikoai/api_resources/fine_tune.py
aikoai/api_resources/image.py
aikoai/api_resources/model.py
aikoai/api_resources/moderation.py
aikoai/api_resources/abstract/__init__.py
aikoai/api_resources/abstract/api_resource.py
aikoai/api_resources/abstract/createable_api_resource.py
aikoai/api_resources/abstract/deletable_api_resource.py
aikoai/api_resources/abstract/engine_api_resource.py
aikoai/api_resources/abstract/listable_api_resource.py
aikoai/api_resources/abstract/nested_resource_class_methods.py
aikoai/api_resources/abstract/updateable_api_resource.py
aikoai/api_resources/experimental/__init__.py
aikoai/api_resources/experimental/completion_config.py
aikoai/datalib/__init__.py
aikoai/datalib/common.py
aikoai/datalib/numpy_helper.py
aikoai/datalib/pandas_helper.py
aikoai/tests/__init__.py
aikoai/tests/test_api_requestor.py
aikoai/tests/test_endpoints.py
aikoai/tests/test_exceptions.py
aikoai/tests/test_file_cli.py
aikoai/tests/test_long_examples_validator.py
aikoai/tests/test_url_composition.py
aikoai/tests/test_util.py
aikoai/tests/asyncio/__init__.py
aikoai/tests/asyncio/test_endpoints.py
aikoai-4.1.dist-info/METADATA
aikoai-4.1.dist-info/WHEEL
aikoai-4.1.dist-info/entry_points.txt
aikoai-4.1.dist-info/top_level.txt
aikoai-4.1.dist-info/zip-safe
aikoai-4.1.dist-info/RECORD
